Metadata-Version: 1.0
Name: SocketSays
Version: 0.1.1
Summary: Easy socket conversations
Home-page: UNKNOWN
Author: UNKNOWN
Author-email: UNKNOWN
License: LICENSE
Platform: UNKNOWN
